snax/__init__.py
snax/attention.py
snax/base.py
snax/checkpoint.py
snax/conditional.py
snax/dataset.py
snax/made.py
snax/nn.py
snax/recurrent.py
snax/test_attention.py
snax/test_checkpoint.py
snax/test_dataset.py
snax/test_made.py
snax/test_recurrent.py
snax/test_train_lib.py
snax/test_utils.py
snax/test_vmapped.py
snax/train_lib.py
snax/utils.py
snax/old/base.py
snax/old/conditional.py
snax/old/nn.py
snax/old/recurrent.py
snaxlib-0.0.34.dist-info/LICENSE
snaxlib-0.0.34.dist-info/METADATA
snaxlib-0.0.34.dist-info/WHEEL
snaxlib-0.0.34.dist-info/top_level.txt
snaxlib-0.0.34.dist-info/RECORD
