Metadata-Version: 2.1
Name: snaxlib
Version: 0.0.34
Summary: A simple deep learning library for JAX.
Author-email: Dieterich Lawson <dieterich.lawson@gmail.com>
License: MIT License
Project-URL: repository, https://github.com/dieterichlawson/snax
Classifier: Programming Language :: Python :: 3.9
Classifier: Programming Language :: Python :: 3.10
Classifier: Programming Language :: Python :: 3.11
Classifier: License :: OSI Approved :: MIT License
Classifier: Operating System :: OS Independent
Classifier: Development Status :: 2 - Pre-Alpha
Requires-Python: >=3.9
License-File: LICENSE
Requires-Dist: jax (>=0.4.6)
Requires-Dist: jaxlib (>=0.4.6)
Requires-Dist: tensorflow-probability
Requires-Dist: chex
Requires-Dist: typing-extensions
Requires-Dist: equinox (>=0.10.3)
Requires-Dist: optax
Requires-Dist: wandb
